tiff_nc/__init__.py
tiff_nc/calculate.py
tiff_nc/translate_data.py
tiff_nc-0.8.3.dist-info/METADATA
tiff_nc-0.8.3.dist-info/WHEEL
tiff_nc-0.8.3.dist-info/entry_points.txt
tiff_nc-0.8.3.dist-info/RECORD
